setup.cfg
setup.py
redmsg/__init__.py
redmsg/exc.py
redmsg/publisher.py
redmsg/subscriber.py
redmsg.egg-info/PKG-INFO
redmsg.egg-info/SOURCES.txt
redmsg.egg-info/dependency_links.txt
redmsg.egg-info/requires.txt
redmsg.egg-info/top_level.txt