Metadata-Version: 1.1
Name: redmsg
Version: 0.2.2
Summary: Simple Redis messaging with playback support
Home-page: https://github.com/ivotkv/redmsg
Author: Ivo Tzvetkov
Author-email: ivotkv@gmail.com
License: MIT
Download-URL: https://github.com/ivotkv/redmsg/tarball/v0.2.2
Keywords: redis,messaging,playback
Platform: UNKNOWN
Classifier: Development Status :: 5 - Production/Stable
Classifier: Intended Audience :: Developers
Classifier: License :: OSI Approved :: MIT License
Classifier: Operating System :: OS Independent
Classifier: Programming Language :: Python :: 2.7
Classifier: Programming Language :: Python :: 3.3
Classifier: Programming Language :: Python :: 3.4
Classifier: Programming Language :: Python :: 3.5
Classifier: Programming Language :: Python :: 3.6
Classifier: Topic :: Software Development
